esrf_statusgui/__init__.py
esrf_statusgui/brain/dataset_selection_logic.py
esrf_statusgui/brain/dct_dataset_browser.py
esrf_statusgui/brain/dct_experiment_logic.py
esrf_statusgui/brain/post_process.py
esrf_statusgui/brain/source_experiment.py
esrf_statusgui/brain/structure.py
esrf_statusgui/data_managment/DCT_crystallo.h5
esrf_statusgui/data_managment/DCT_parametersDB.h5
esrf_statusgui/data_managment/dct_parameter.py
esrf_statusgui/data_managment/dct_parameter_config.py
esrf_statusgui/data_managment/dct_parameter_schema.py
esrf_statusgui/data_managment/dct_parameter_template.py
esrf_statusgui/data_managment/loadFile.py
esrf_statusgui/exp_methods/MasterClass_Status.py
esrf_statusgui/exp_methods/dct_status.py
esrf_statusgui/exp_methods/ff_status.py
esrf_statusgui/exp_methods/s3DXRD_status.py
esrf_statusgui/exp_methods/status.json
esrf_statusgui/exp_methods/tomography_status.py
esrf_statusgui/exp_methods/dct/gtFsimCheckMissingGrains.py
esrf_statusgui/exp_methods/dct/matlab_engine.py
esrf_statusgui/file_utils/FolderPermissionChecker.py
esrf_statusgui/file_utils/createProcessingNotebook.py
esrf_statusgui/file_utils/fileNode.py
esrf_statusgui/file_utils/file_utils.py
esrf_statusgui/file_utils/newExperimentDate.py
esrf_statusgui/file_utils/paths.py
esrf_statusgui/notebooks/dct/Tuto_1_SetupDCT.ipynb
esrf_statusgui/notebooks/dct/Tuto_2_ProcessDCT.ipynb
esrf_statusgui/notebooks/imaged11/S3DXRD/0_segment_and_label.ipynb
esrf_statusgui/notebooks/imaged11/S3DXRD/0_segment_frelon.ipynb
esrf_statusgui/notebooks/imaged11/S3DXRD/4_visualise.ipynb
esrf_statusgui/notebooks/imaged11/S3DXRD/5_combine_phases.ipynb
esrf_statusgui/notebooks/imaged11/S3DXRD/6_run_papermill.ipynb
esrf_statusgui/notebooks/imaged11/S3DXRD/7_stack_layers.ipynb
esrf_statusgui/notebooks/imaged11/S3DXRD/__init__.py
esrf_statusgui/notebooks/imaged11/S3DXRD/friedel_pair_map.ipynb
esrf_statusgui/notebooks/imaged11/S3DXRD/import_test_data.ipynb
esrf_statusgui/notebooks/imaged11/S3DXRD/pbp_1_indexing.ipynb
esrf_statusgui-0.3.0.dist-info/licenses/LICENSE.md
esrf_statusgui-0.3.0.dist-info/METADATA
esrf_statusgui-0.3.0.dist-info/WHEEL
esrf_statusgui-0.3.0.dist-info/entry_points.txt
esrf_statusgui-0.3.0.dist-info/top_level.txt
esrf_statusgui-0.3.0.dist-info/RECORD
