Metadata-Version: 2.4
Name: esrf-statusgui
Version: 0.3.0
Summary: Get the post-treatment progress of any ESRF-ID11 experiment. Option to launch the post-treatment from the GUI.
Author-email: Charles ROMAIN <charles.romain@protonmail.com>
License-Expression: MIT
Project-URL: Homepage, https://gitlab.esrf.fr/graintracking/statusgui
Project-URL: Repository, https://gitlab.esrf.fr/graintracking/statusgui
Project-URL: Issues, https://gitlab.esrf.fr/graintracking/statusgui/-/issues
Project-URL: Changelog, https://gitlab.esrf.fr/graintracking/statusgui/-/blob/dev/CHANGELOG.md
Keywords: ESRF,Jupyter,widgets,diffraction,tomography,beamline
Classifier: Development Status :: 4 - Beta
Classifier: Intended Audience :: Science/Research
Classifier: Programming Language :: Python :: 3
Classifier: Programming Language :: Python :: 3 :: Only
Classifier: Programming Language :: Python :: 3.9
Classifier: Programming Language :: Python :: 3.10
Classifier: Programming Language :: Python :: 3.11
Classifier: Programming Language :: Python :: 3.12
Classifier: Operating System :: POSIX :: Linux
Classifier: Framework :: Jupyter
Classifier: Framework :: Jupyter :: JupyterLab
Classifier: Topic :: Scientific/Engineering
Classifier: Topic :: Scientific/Engineering :: Physics
Requires-Python: >=3.9
License-File: LICENSE.md
Requires-Dist: silx
Requires-Dist: numpy
Requires-Dist: scipy
Requires-Dist: tqdm
Requires-Dist: h5py
Requires-Dist: esrf-loadfile>=0.1.0
Requires-Dist: json5
Requires-Dist: pandas
Requires-Dist: fasteners
Requires-Dist: matplotlib
Requires-Dist: nbformat
Requires-Dist: esrf-pathlib>=0.5.0
Requires-Dist: mysqlclient
Provides-Extra: dev
Requires-Dist: ruff>=0.4.0; extra == "dev"
Requires-Dist: mypy>=1.8.0; extra == "dev"
Requires-Dist: pytest; extra == "dev"
Requires-Dist: bandit; extra == "dev"
Requires-Dist: black; extra == "dev"
Requires-Dist: flake8; extra == "dev"
Requires-Dist: flake8-pep585; extra == "dev"
Requires-Dist: pre-commit; extra == "dev"
Requires-Dist: pytest-cov; extra == "dev"
Requires-Dist: pytest-mock; extra == "dev"
Requires-Dist: pytest-profiling!=1.8.0; extra == "dev"
Requires-Dist: pytest-rerunfailures; extra == "dev"
Requires-Dist: pytest-xvfb; extra == "dev"
Requires-Dist: scriv>=1.3.1; extra == "dev"
Requires-Dist: build; extra == "dev"
Requires-Dist: twine; extra == "dev"
Provides-Extra: dev-rust
Requires-Dist: maturin>=1.4.0; extra == "dev-rust"
Requires-Dist: setuptools-rust>=1.8.1; extra == "dev-rust"
Provides-Extra: gui
Requires-Dist: ipykernel; extra == "gui"
Requires-Dist: ipywidgets; extra == "gui"
Requires-Dist: ipympl; extra == "gui"
Requires-Dist: matplotlib-inline; extra == "gui"
Provides-Extra: jupyter
Requires-Dist: esrf-statusgui[gui]; extra == "jupyter"
Requires-Dist: jupyterhub; extra == "jupyter"
Requires-Dist: jupyterlab; extra == "jupyter"
Requires-Dist: batchspawner; extra == "jupyter"
Provides-Extra: full
Requires-Dist: esrf-statusgui[dev]; extra == "full"
Requires-Dist: esrf-statusgui[dev-rust]; extra == "full"
Requires-Dist: esrf-statusgui[gui]; extra == "full"
Provides-Extra: extra
Requires-Dist: ImageD11==2.1.2; extra == "extra"
Requires-Dist: dct>=0.0.2; extra == "extra"
Requires-Dist: Dans-Diffraction; extra == "extra"
Provides-Extra: all
Requires-Dist: esrf-statusgui[jupyter]; extra == "all"
Requires-Dist: esrf-statusgui[full]; extra == "all"
Requires-Dist: esrf-statusgui[extra]; extra == "all"
Dynamic: license-file
